nostromo_api/__init__.py
nostromo_api/auth.py
nostromo_api/config.py
nostromo_api/errors.py
nostromo_api/main.py
nostromo_api/websocket.py
nostromo_api/routes/__init__.py
nostromo_api/routes/auth.py
nostromo_api/routes/chat.py
nostromo_api/routes/health.py
nostromo_api/routes/sessions.py
nostromo_api-0.1.0.dist-info/METADATA
nostromo_api-0.1.0.dist-info/WHEEL
nostromo_api-0.1.0.dist-info/entry_points.txt
nostromo_api-0.1.0.dist-info/RECORD
