Metadata-Version: 2.4
Name: nostromo-api
Version: 0.1.0
Summary: MU-TH-UR 6000 REST API - Aliens-themed chatbot API server
Author: Nostromo Crew
License: MIT
Keywords: aliens,api,chatbot,fastapi,llm,mother
Requires-Python: >=3.11
Requires-Dist: fastapi>=0.115.0
Requires-Dist: nostromo-core
Requires-Dist: passlib[bcrypt]>=1.7.4
Requires-Dist: pydantic-settings>=2.0.0
Requires-Dist: python-jose[cryptography]>=3.3.0
Requires-Dist: python-multipart>=0.0.9
Requires-Dist: sse-starlette>=2.0.0
Requires-Dist: uvicorn[standard]>=0.32.0
Provides-Extra: all
Requires-Dist: anthropic>=0.40.0; extra == 'all'
Requires-Dist: openai>=1.0.0; extra == 'all'
Provides-Extra: anthropic
Requires-Dist: anthropic>=0.40.0; extra == 'anthropic'
Provides-Extra: dev
Requires-Dist: httpx>=0.27.0; extra == 'dev'
Requires-Dist: pytest-asyncio>=0.23.0; extra == 'dev'
Requires-Dist: pytest>=8.0.0; extra == 'dev'
Provides-Extra: openai
Requires-Dist: openai>=1.0.0; extra == 'openai'
